{
  "gym": [
    {
      "id": "63346066b9d2dcd50ef23b8f",
      "name": "Jumping Jack",
      "img": "https://unsplash.com/photos/7QYd1VxLRbM",
      "descrip": "A standing person jumps to a position with the legs and arms spread out and then jumps back to the original position.",
      "age": 24,
      "time": 15
    },
    {
      "id": "633460668bcbbbc26bf33c05",
      "name": "Cobra Stretch",
      "img": "https://unsplash.com/photos/cuOHHP5tx5g",
      "descrip": "A heart-opening backbend that stretches your entire upper body",
      "age": 22,
      "time": 17
    },
    {
      "id": "6334606653aa5192cab880b4",
      "name": "Chest Stretch",
      "img": "https://unsplash.com/photos/RKrwVMiW-ik",
      "descrip": "With the side of your body facing a wall, place your left palm on the wall.",
      "age": 24,
      "time": 20
    },
    {
      "id": "633460665a0e6bdebcad0c2d",
      "name": "Russian Twist",
      "img": "https://unsplash.com/photos/0HlI76m4jxU",
      "descrip": "Aitting with your legs bent and your lower back straight",
      "age": 24,
      "time": 18
    },
    {
      "id": "63346066451681f638a950be",
      "name": "Plank",
      "img": "https://unsplash.com/photos/zbF-lW3k1QU",
      "descrip": "A long, narrow, flat piece of wood or similar material, of the type used for making floors",
      "age": 24,
      "time": 20
    },
    {
      "id": "6334606613eee71629dd9e95",
      "name": "Arm Raises",
      "img": "https://unsplash.com/photos/nKCtkaW4JU4",
      "descrip": "Exercise designed to strengthen the arm muscles",
      "age": 21,
      "time": 17
    }
  ]
}